autocopyright/__init__.py
autocopyright/__main__.py
autocopyright-1.1.0.dist-info/entry_points.txt
autocopyright-1.1.0.dist-info/LICENSE.md
autocopyright-1.1.0.dist-info/METADATA
autocopyright-1.1.0.dist-info/WHEEL
autocopyright-1.1.0.dist-info/RECORD
