Metadata-Version: 2.1
Name: autocopyright
Version: 1.1.0
Summary: Script for adding copyright notes at the top of files.
Home-page: https://github.com/Argmaster/autocopyright
Author: Krzysztof Wiśniewski
Author-email: argmaster.world@gmail.com
Requires-Python: >=3.9,<4.0
Classifier: Programming Language :: Python :: 3
Classifier: Programming Language :: Python :: 3.9
Classifier: Programming Language :: Python :: 3.10
Classifier: Programming Language :: Python :: 3.11
Requires-Dist: click (>=8.1.3,<9.0.0)
Requires-Dist: jellyfish (>=0.9.0,<0.10.0)
Requires-Dist: jinja2 (>=3.1.2,<4.0.0)
Requires-Dist: tomlkit (>=0.11.6,<0.12.0)
Project-URL: Repository, https://github.com/Argmaster/autocopyright
